LICENSE
MANIFEST.in
README.md
requirements.txt
setup.cfg
setup.py
annofilt/__init__.py
annofilt/_version.py
annofilt/annofilt.py
annofilt/get_complete_genomes.py
annofilt/make_annofilt_pangenome.py
annofilt/shared_methods.py
annofilt/test_unitprot.py
annofilt.egg-info/PKG-INFO
annofilt.egg-info/SOURCES.txt
annofilt.egg-info/dependency_links.txt
annofilt.egg-info/entry_points.txt
annofilt.egg-info/requires.txt
annofilt.egg-info/top_level.txt