Metadata-Version: 1.1
Name: annofilt
Version: 0.0.8
Summary: Filter annotations from prokka
Home-page: https://github.com/nickp60/annofilt
Author: Nick Waters
Author-email: nickp60@gmail.com
License: MIT
Keywords: bioinformatics assembly genomics development
Platform: UNKNOWN
Classifier: Development Status :: 3 - Alpha
Classifier: Intended Audience :: Developers
Classifier: Intended Audience :: Science/Research
Classifier: License :: OSI Approved :: MIT License
Classifier: Programming Language :: Python :: 3.5
Classifier: Programming Language :: Python :: 3.6
